nocaselist/__init__.py
nocaselist/_nocaselist.py
nocaselist/_version.py
nocaselist/_version_scm.py
nocaselist/py.typed
nocaselist-2.2.0.dist-info/licenses/LICENSE
nocaselist-2.2.0.dist-info/METADATA
nocaselist-2.2.0.dist-info/WHEEL
nocaselist-2.2.0.dist-info/top_level.txt
nocaselist-2.2.0.dist-info/zip-safe
nocaselist-2.2.0.dist-info/RECORD
