Metadata-Version: 2.4
Name: nocaselist
Version: 2.2.0
Summary: A case-insensitive list for Python
Author-email: Andreas Maier <maiera@de.ibm.com>
Maintainer-email: Andreas Maier <maiera@de.ibm.com>
License-Expression: Apache-2.0
Project-URL: Homepage, https://github.com/pywbem/nocaselist
Project-URL: Bug Tracker, https://github.com/pywbem/nocaselist/issues
Project-URL: Documentation, https://nocaselist.readthedocs.io/en/master/
Project-URL: Source Code, https://github.com/pywbem/nocaselist
Project-URL: Changelog, https://nocaselist.readthedocs.io/en/master/changes.html
Keywords: list,case-insensitive
Platform: any
Classifier: Development Status :: 5 - Production/Stable
Classifier: Intended Audience :: Developers
Classifier: Operating System :: OS Independent
Classifier: Programming Language :: Python :: 3
Classifier: Programming Language :: Python :: 3.9
Classifier: Programming Language :: Python :: 3.10
Classifier: Programming Language :: Python :: 3.11
Classifier: Programming Language :: Python :: 3.12
Classifier: Programming Language :: Python :: 3.13
Classifier: Programming Language :: Python :: 3.14
Classifier: Topic :: Software Development :: Libraries :: Python Modules
Requires-Python: >=3.9
License-File: LICENSE
Requires-Dist: typing-extensions>=4.14.1
Dynamic: license-file
